distify/__init__.py
distify/_core.py
distify/_utils.py
distify/contrib.py
distify-0.8.5.dist-info/LICENSE
distify-0.8.5.dist-info/METADATA
distify-0.8.5.dist-info/WHEEL
distify-0.8.5.dist-info/top_level.txt
distify-0.8.5.dist-info/RECORD
