Metadata-Version: 2.1
Name: distify
Version: 0.8.5
Summary: Easy wrapper for parallelizing Python executions
Home-page: https://github.com/jordiae/distify
Author: Jordi Armengol-Estapé
Author-email: me@jordiae.com
License: MIT
Platform: UNKNOWN
Classifier: License :: OSI Approved :: MIT License
Classifier: Programming Language :: Python :: 3
Classifier: Programming Language :: Python :: 3.7
Classifier: Programming Language :: Python :: 3.8
Classifier: Programming Language :: Python :: 3.9
Classifier: Programming Language :: Python :: 3.0
License-File: LICENSE
Requires-Dist: ray
Requires-Dist: hydra-core
Requires-Dist: hydra-ray-launcher
Requires-Dist: tqdm
Requires-Dist: aiohttp (>=3.7)
Requires-Dist: sqlitedict
Requires-Dist: ordered-set
